Metadata-Version: 1.1
Name: InternetFileDownloader
Version: 2021.1.2
Summary: This is a file downloader.
Home-page: UNKNOWN
Author: Pranav
Author-email: UNKNOWN
License: UNKNOWN
Platform: UNKNOWN
Classifier: Programming Language :: Python :: 3.9
Classifier: License :: OSI Approved :: MIT License
Classifier: Operating System :: OS Independent
